clients_core/__init__.py
clients_core/api_match_client.py
clients_core/exceptions.py
clients_core/models.py
clients_core/rest_client.py
clients_core/secured_rest_client.py
clients_core/service_clients.py
clients_core/service_list_provider.py
clients_core/settings.py
clients_core/simple_rest_client.py
clients_core/utils.py
clients_core/authentication/__init__.py
clients_core/authentication/cache.py
clients_core/authentication/token_cache.py
clients_core/authentication/token_handler.py
clients_core-3.0.2.dist-info/LICENSE.txt
clients_core-3.0.2.dist-info/METADATA
clients_core-3.0.2.dist-info/WHEEL
clients_core-3.0.2.dist-info/top_level.txt
clients_core-3.0.2.dist-info/RECORD
