Metadata-Version: 2.2
Name: clients_core
Version: 3.0.2
Summary: A collection of Python connection clients for E360 Microservices
Author: IQVIA
Author-email: e360pypi@iqvia.com
License: Apache License 2.0
Classifier: Environment :: Web Environment
Classifier: Intended Audience :: Developers
Classifier: License :: OSI Approved :: Apache Software License
Classifier: Operating System :: OS Independent
Classifier: Programming Language :: Python
Classifier: Programming Language :: Python :: 3.9
Classifier: Programming Language :: Python :: 3.10
Classifier: Programming Language :: Python :: 3.11
Classifier: Topic :: Internet :: WWW/HTTP
Classifier: Topic :: Internet :: WWW/HTTP :: Dynamic Content
Requires-Python: >=3.9
License-File: LICENSE.txt
Requires-Dist: oauthlib
Requires-Dist: pydantic<3,>=2
Requires-Dist: pydantic-settings
Requires-Dist: redis
Requires-Dist: requests
Requires-Dist: requests-oauthlib
Requires-Dist: semver
Requires-Dist: simplejson
Dynamic: author
Dynamic: author-email
Dynamic: classifier
Dynamic: license
Dynamic: requires-dist
Dynamic: requires-python
Dynamic: summary
